{
  "doc_id": "CRA1XK8 - all the extras our best accessories\\Headers\\CRA1XK8_00.txt",
  "doc_path": "C:\\Users\\ASUS\\Desktop\\Outlook\\CRA1XK8 - all the extras our best accessories\\Headers\\CRA1XK8_00.txt",
  "num_chunks": 1,
  "chunks": [
    {
      "text": "Received: from AM9PR05MB8663.eurprd05.prod.outlook.com (2603:10a6:20b:41a::20) by AS8PR05MB10824.eurprd05.prod.outlook.com with HTTPS; Wed, 16 Oct 2024 14:26:38 +0000\nReceived: from DUZPR01CA0254.eurprd01.prod.exchangelabs.com (2603:10a6:10:4b5::26) by AM9PR05MB8663.eurprd05.prod.outlook.com (2603:10a6:20b:41a::20) with Microsoft SMTP Server (version=TLS1_2, cipher=TLS_ECDHE_RSA_WITH_AES_256_GCM_SHA384) id 15.20.7982.34; Wed, 16 Oct 2024 14:26:35 +0000\nReceived: from DU2PEPF00028CFC.eurprd03.prod.outlook.com (2603:10a6:10:4b5:cafe::97) by DUZPR01CA0254.outlook.office365.com (2603:10a6:10:4b5::26) with Microsoft SMTP Server (version=TLS1_2, cipher=TLS_ECDHE_RSA_WITH_AES_256_GCM_SHA384) id 15.20.8069.18 via Frontend Transport; Wed, 16 Oct 2024 14:26:35 +0000\nAuthentication-Results: spf=pass (sender IP is 149.72.231.7) smtp.mailfrom=env.e.levelshoes.com; dkim=pass (signature was verified) header.d=e.levelshoes.com;dmarc=pass action=none header.from=e.levelshoes.com;compauth=pass reason=100\nReceived-SPF: Pass (protection.outlook.com: domain of env.e.levelshoes.com designates 149.72.231.7 as permitted sender) receiver=protection.outlook.com; client-ip=149.72.231.7; helo=o1479.e.levelshoes.com; pr=C\nReceived: from o1479.e.levelshoes.com (149.72.231.7) by DU2PEPF00028CFC.mail.protection.outlook.com (10.167.242.180) with Microsoft SMTP Server (version=TLS1_3, cipher=TLS_AES_256_GCM_SHA384) id 15.20.8069.17 via Frontend Transport; Wed, 16 Oct 2024 14:26:34 +0000\nDKIM-Signature: v=1; a=rsa-sha256; c=relaxed/relaxed; d=e.levelshoes.com; h=content-transfer-encoding:content-type:from:mime-version:subject: reply-to:list-unsubscribe:list-unsubscribe-post:to:cc:content-type:from: subject:to; s=m1; bh=D8h7t8nsWxjhikz6lMRzsakGuBC6bHkrdwTVQeHgGxY=; b=NfGOAAg3PIP9m9pKcrD1ULFTQdPPy3ZatfkovAFSCyTWWef8FvMRxnVhloH1SNvR/ycm j7P107jh/7MJKxB9PYB4RO8FRT6437aWkd60xPBWYvLqKgBFLKqix7RGJc5dclyma1tkdZ czRAK5vr7NwhRSVF3bpbyCzB34C0AiGNCUVVx5+4KRt9cn5cO/tYTagF5xUkaDbzdnvx3l GiaVu9RLkUgM65NpvxM9osV5KJR+cY36ffLQoITSK3Z8U6ZfW/6DEO5R9eqJTXGgNEj0v4 u0Lrq+5ZOQu8lgsyNltMHQ5bUQR0/irAHkLL0ZrdoQyH0wsGgq/pLNEyCnUEUquw==\nReceived: by recvd-65bdd88ff5-tgn7z with SMTP id recvd-65bdd88ff5-tgn7z-1-670FCD19-17 2024-10-16 14:26:33.157621815 +0000 UTC m=+2924937.992627338\nReceived: from MzM2Mzk0NDY (unknown) by geopod-ismtpd-1 (SG) with HTTP id ImNXts9WQc2xhU5CDf7vCg Wed, 16 Oct 2024 14:26:33.153 +0000 (UTC)\nContent-Transfer-Encoding: quoted-printable\nContent-Type: text/html; charset=utf-8\nDate: Wed, 16 Oct 2024 14:26:33 +0000 (UTC)\nFrom: Level Shoes <newsletter@e.levelshoes.com>\nMime-Version: 1.0\nMessage-ID: <ImNXts9WQc2xhU5CDf7vCg@geopod-ismtpd-1>\nSubject: All the Extras: Our Best Accessories\nReply-To: guestservices@levelshoes.com\nx-campaignid: 670fbe1cb2c7bbb24951e9c9\nList-Unsubscribe: =?us-ascii?Q?=3Cmailto=3Aunsubscribe=40env=2Ee=2Elevelshoes=2Ecom=3Fsubject=3Dhttps=3A=2F=2Flinks?= =?us-ascii?Q?g=2Elevelshoes=2Ecom=2Fss=2Fsu=2Fu001=2EJsQTCX5jqhl?= =?us-ascii?Q?m3h33UBFkzw=2F4an=2FJwR65k9CTp6BgoDSsyc=5FHg=2F?= =?us-ascii?Q?um=2Fh001=2E=5F3DREA6QTFAsMTtHoYaTvtFqky80-Ht?= =?us-ascii?Q?XLZrwjvTZJ7Y=3E=2C=3Chttps=3A=2F=2Flinksg=2Elevelshoe?= =?us-ascii?Q?s=2Ecom=2Flu=2Funsubscribe=3Foc=3Du001=2E=5FdNPZ=5F-3Bo?= =?us-ascii?Q?lqzs-IpP6tM2-bc3z7yDgMb92F0phv5ig79Ge2K?= =?us-ascii?Q?erFCVkjtrX8Q2mpL=5F7S9MOrBeAoEoifj29x90l5?= =?us-ascii?Q?JRwpp54a6c4ei3vnTDUsOIjqkjtiaw5vQrdq6QD?= =?us-ascii?Q?Dr13Y14EFVdr-f0KeREfcTgOlcqUbY=5Fbr=5FFJTfC?= =?us-ascii?Q?IAinrf4KegNOuuUEcZ-egQpPPrCp=5FkzEIBZ1IHS?= =?us-ascii?Q?XDkp4rmSw=3E?=\nList-Unsubscribe-Post: List-Unsubscribe=One-Click\nX-SG-EID: =?us-ascii?Q?u001=2E79kJZC85z=2FWE9t9nOmpiHpXtZHMVNEq8Mf4PPBnEgiNbWR08kHbx0Rf4d?= =?us-ascii?Q?I08wUMMigYFicz2IRkRWrk1UolhGQ9V66YyWonx?= =?us-ascii?Q?My+PHDqpT8ffxdhK=2FB1nYMalLvwdtEZzn4ImoSd?= =?us-ascii?Q?a+ghNm8jvgOwf66+3bMfqnEHqfcTJkyWb6+6a8Q?= =?us-ascii?Q?2KhcxT9bVB3=2F9ExPxIhVJGNLfDaw8lxfA5pvqNa?= =?us-ascii?Q?HfE0TzPN=2FYEKz6Rqru1uRRnZOHOde=2FufPm3EGsk?= =?us-ascii?Q?oggULyv=2FPO98RCDnMmLuXHEiTg=3D=3D?=\nX-SG-ID: =?us-ascii?Q?u001=2ESdBcvi+Evd=2FbQef8eZF3BpTL9BgbK5wfSJMJGMsmprBkkoo3Jz4rspq=2Fx?= =?us-ascii?Q?5d35vN=2FaxQFFJdoGSmRINuE8bW76jq1hHnRWX+h?= =?us-ascii?Q?ZbKmqHNjU9vLYdxvX3bfZHqVZF=2Fg9qWaTW6NnO=2F?= =?us-ascii?Q?MTUog45PgU8ywqUDyFNaUVEIhZZiFwBVKptAx6O?= =?us-ascii?Q?Ze9oohVJvSbxBo1J8j10TQc2+OuSkS4HgNFQA=2F1?= =?us-ascii?Q?hld6hJt1sxoUDVcVm3Ql7YRwHvrXato=2FL0YuG+4?= =?us-ascii?Q?Uzx5=2FyIqtEue4Ci83mSNI28d30C63Tq1tdm1N3l?= =?us-ascii?Q?sxXhEIY1X0Ooxfz4A4IElZqLnz7SO=2FvnjS6vu8G?= =?us-ascii?Q?FWG12zCoPQD1rehVRRgHqQzFY1fqZ=2FaYI1ZqEYG?= =?us-ascii?Q?vHdjJzcpVhTovylVCJdoeyX27sNsiQcyqasppsX?= =?us-ascii?Q?MxxeEmTlCNwEXQWVUVE=3D?=\nTo: hagop.ghazarian@chalhoub.com\nX-Entity-ID: u001.Bm2BswNpqGj1jpw5gGV4+A==\nReturn-Path: bounces+33639446-8684-hagop.ghazarian=chalhoub.com@env.e.levelshoes.com\nX-MS-Exchange-Organization-ExpirationStartTime: 16 Oct 2024 14:26:35.3580 (UTC)\nX-MS-Exchange-Organization-ExpirationStartTimeReason: OriginalSubmit\nX-MS-Exchange-Organization-ExpirationInterval: 1:00:00:00.0000000\nX-MS-Exchange-Organization-ExpirationIntervalReason: OriginalSubmit\nX-MS-Exchange-Organization-Network-Message-Id: a7139917-25d4-4a06-8088-08dcedee8a08\nX-EOPAttributedMessage: 0\nX-EOPTenantAttributedMessage: 6ef8304c-f37b-42a5-a569-0a7d8249fbf3:0\nX-MS-Exchange-Organization-MessageDirectionality: Incoming\nX-MS-PublicTrafficType: Email\nX-MS-TrafficTypeDiagnostic: DU2PEPF00028CFC:EE_|AM9PR05MB8663:EE_|AS8PR05MB10824:EE_\nX-MS-Exchange-Organization-AuthSource: DU2PEPF00028CFC.eurprd03.prod.outlook.com\nX-MS-Exchange-Organization-AuthAs: Anonymous\nX-MS-Office365-Filtering-Correlation-Id: a7139917-25d4-4a06-8088-08dcedee8a08\nX-MS-Exchange-AtpMessageProperties: SA|SL\nX-MS-Exchange-Organization-SCL: 1\nX-Microsoft-Antispam: BCL:3;ARA:13230040|3092899012|3072899012|2092899012|12012899012|69100299015|4022899009|29132699027|5062899012|1032899013|8096899003|2066899003;\nX-Forefront-Antispam-Report: CIP:149.72.231.7;CTRY:US;LANG:en;SCL:1;SRV:;IPV:NLI;SFV:NSPM;H:o1479.e.levelshoes.com;PTR:o1479.e.levelshoes.com;CAT:NONE;SFS:(13230040)(3092899012)(3072899012)(2092899012)(12012899012)(69100299015)(4022899009)(29132699027)(5062899012)(1032899013)(8096899003)(2066899003);DIR:INB;\nX-MS-Exchange-CrossTenant-OriginalArrivalTime: 16 Oct 2024 14:26:34.8111 (UTC)\nX-MS-Exchange-CrossTenant-Network-Message-Id: a7139917-25d4-4a06-8088-08dcedee8a08\nX-MS-Exchange-CrossTenant-Id: 6ef8304c-f37b-42a5-a569-0a7d8249fbf3\nX-MS-Exchange-CrossTenant-AuthSource: DU2PEPF00028CFC.eurprd03.prod.outlook.com\nX-MS-Exchange-CrossTenant-AuthAs: Anonymous\nX-MS-Exchange-CrossTenant-FromEntityHeader: Internet\nX-MS-Exchange-Transport-CrossTenantHeadersStamped: AM9PR05MB8663\nX-MS-Exchange-Transport-EndToEndLatency: 00:00:03.7384218\nX-MS-Exchange-Processed-By-BccFoldering: 15.20.7982.032\nX-Microsoft-Antispam-Mailbox-Delivery: ucf:0;jmr:0;auth:0;dest:I;ENG:(910001)(944506478)(944626604)(920097)(930097)(140003)(1420198);\nX-Microsoft-Antispam-Message-Info: =?us-ascii?Q?655f6Xf+BiHffN+RteUqYIWxurTMTSsmFonKzLqjTNVA5E5wt/96Oev8++B3?= =?us-ascii?Q?0NpxFUkK6YgG2Dj98ETuyAoaN7BxkcIO0C6f4d0kvijdydr6eYPtvuAXTCQ7?= =?us-ascii?Q?qznDzWzzm0ujetmzEkGYE4CUgn559aDc/VoWPytQHNBMXXI8W5syDwZi9/y6?= =?us-ascii?Q?dvJVUCL+HY7d1rEkcWZUnCId5S0K+JY8FGvIz7PoScrJZXLVReJIi8naZYRV?= =?us-ascii?Q?4fF0WCwj/PWi03WCLBIHGi8tNe6V1oH+yGIK2Cj2Dvtj6mvmxRMbEBVUGzUx?= =?us-ascii?Q?LjhOjzhKSC1qPwgimTFyPDAy2p9FGHxlhJlvzUZkydYRDng2cXwUd1wMaodl?= =?us-ascii?Q?/omaSiPam7o8mpZi4Njkx3L5xoeTaWKmOkYJ7ohQBpFNpEGvcvJXYn2BYWi6?= =?us-ascii?Q?csxgER+5Wto9RTHxWtHSfhzw0v3qpMIQJkf0Xez0sNG1/xvHG5GFOmLg6s5I?= =?us-ascii?Q?+3i+A60P5TlOrVT/aL34w/qYJYxjbRQpTJ8sh3Ai5hEhF7/DAeEggdgk7tkb?= =?us-ascii?Q?q4g0d/vcpPdDdP7GBjZ0cwcGmwoVXW2VLYAqJoSeXGom45S23NYUgsFyUshv?= =?us-ascii?Q?7GEHRdk6FOvVPg8oC9TrWavJKF+KB++jQ20Ey/GnWcdUuemEGRs2gfMlQPf9?= =?us-ascii?Q?/chzk8ikkTJIRpHE0VG5U7i0t+j/d/T/mUVg57VbVM5rB5Tlg2+5jwZu/VTH?= =?us-ascii?Q?OBDgPcGkpk6JY+28yjPQWPNvrkEUbaQ4vbh782A+yEHe0e2uln7eLwg2CcYW?= =?us-ascii?Q?WfJz1gAEi2bTt4tMUKQN+VUhOwDXdI1wv/MxiDRxhXi1dgoYPpBztymgnI/M?= =?us-ascii?Q?7WYAHp3STNRnzujFgZoYfJFnCX6XaKLERHr/IxBmLkqSY4yeKWKMX1MrTPPO?= =?us-ascii?Q?zpNRc19ZwVv376l06KCMqSHzy/x4CgET3fzTDqQgb1TifaNlC/26szpfxWuJ?= =?us-ascii?Q?XCR5T49ZYzOlQvMNBYLdjUZumKqQyCqFwsM53HUWG5iGJNcUYkKXsVpSMFfh?= =?us-ascii?Q?dvCwv9IrbUXCWcwdaecdpRH1waXg2gJXWgY4zEnnhHNpiQW9QkItQXTwMacp?= =?us-ascii?Q?iCcWziGjiVnHCFEqLqEFVAPcO5Thw2GWEMyckk9+VapwZmdFm/afWas4WBlf?= =?us-ascii?Q?n6jJ0Eed70y5EfO8ilMIrKvcx1GXCQBzLxkxHlNUraXbe4jbwngyBK1QGECJ?= =?us-ascii?Q?mq5PMWlbIXfSgDsVRSu8ViyWxPGJPOL9xg7fit+TlYS6Mxow9Ow3/ZZi2loF?= =?us-ascii?Q?Kpd+RLVkDMV6c9rDWqeyT7nf19vgOG8FWFOhwx1R+vOvT8wQOU8P8wz4sTyR?= =?us-ascii?Q?LJK3Fy+RtzHOZYxOitU4SzxxJnfEQw/0RRlCVrdMOt/xyv56hiyUXFOmc3Ac?= =?us-ascii?Q?09WIZMoK3xsG7PP5U6bGEhgDuHM/9w/WWNcGc1zcCx6I42TOyTe9GMQGGrE8?= =?us-ascii?Q?o7tsbTFBV7hY1m8FS8uZwSZB5SrwHkHjGlWxFz4WOZgLk1YxyaFz7fJDVIFH?= =?us-ascii?Q?aws9e3WCgyHSKz53+BQeEXQvLzZ5HfBerkcmgd4FGDLDp3AVVmA6LcKyYdDE?= =?us-ascii?Q?JfnD8PHGkCWtyE8HY6c4xVkw+ZMWZg5lWYo6v5cLCTEcmWHCRuZnKhxN4ybP?= =?us-ascii?Q?y14wnzI69yiCBWx9mJjNoTMgnRq+ZXXaO0J+AhX7J5XMAK2vmOILeDip7sY2?= =?us-ascii?Q?4VqUl7fqW609IgDGa4ZgvbqbXrLu83scJiqS27CU4TUMR62y7msMCxgmV7Ya?= =?us-ascii?Q?JhyQzsQSVEqYXgSGpEHo+mrQpAA9XCWIf6Oj85Q8qmjRfjS4XQfNeJNIK87p?= =?us-ascii?Q?CSHmAqbOsdj9hhEJhY3aadi6qNY192LbSvOgnS/JPZGK8Sj/DfGVv2XHP9tm?= =?us-ascii?Q?jKTZANURK6efn7sh9T8E11zual7mGQI4XH2EymFwa4tbzwGLfURiRdBMaOyz?=",
      "start_pos": 0,
      "end_pos": 9382,
      "chunk_index": 0,
      "chunk_size": 9382,
      "metadata": {
        "doc_id": "CRA1XK8 - all the extras our best accessories\\Headers\\CRA1XK8_00.txt",
        "doc_path": "C:\\Users\\ASUS\\Desktop\\Outlook\\CRA1XK8 - all the extras our best accessories\\Headers\\CRA1XK8_00.txt"
      }
    }
  ],
  "metadata": {
    "chunked_at": "2025-10-06T06:26:57.085903",
    "chunk_config": {
      "chunk_size": 1600,
      "chunk_overlap": 200,
      "min_chunk_size": 100,
      "respect_sentences": true,
      "respect_paragraphs": true,
      "base_max_chunks": 25,
      "progressive_scaling": true
    },
    "original_size": 9439
  }
}