{
  "doc_id": "C1ER4UL - new available office space 10 floor al jazira tower\\Headers\\C1ER4UL_08.txt",
  "doc_path": "C:\\Users\\ASUS\\Desktop\\Outlook\\C1ER4UL - new available office space 10 floor al jazira tower\\Headers\\C1ER4UL_08.txt",
  "num_chunks": 3,
  "chunks": [
    {
      "text": "Received: from VI0PR05MB11320.eurprd05.prod.outlook.com (::1) by AS8PR05MB10824.eurprd05.prod.outlook.com with HTTPS; Fri, 27 Sep 2024 08:48:46 +0000\nReceived: from AS4P190CA0005.EURP190.PROD.OUTLOOK.COM (2603:10a6:20b:5de::17) by VI0PR05MB11320.eurprd05.prod.outlook.com (2603:10a6:800:210::6) with Microsoft SMTP Server (version=TLS1_2, cipher=TLS_ECDHE_RSA_WITH_AES_256_GCM_SHA384) id 15.20.7982.25; Fri, 27 Sep 2024 08:45:23 +0000\nReceived: from AM4PEPF00027A61.eurprd04.prod.outlook.com (2603:10a6:20b:5de:cafe::45) by AS4P190CA0005.outlook.office365.com (2603:10a6:20b:5de::17) with Microsoft SMTP Server (version=TLS1_2, cipher=TLS_ECDHE_RSA_WITH_AES_256_GCM_SHA384) id 15.20.8005.22 via Frontend Transport; Fri, 27 Sep 2024 08:45:21 +0000\nAuthentication-Results: spf=pass (sender IP is 104.209.35.28) smtp.mailfrom=chalhoub.com; dkim=none (message not signed) header.d=none;dmarc=pass action=none header.from=chalhoub.com;\nReceived-SPF: Pass (protection.outlook.com: domain of chalhoub.com designates 104.209.35.28 as permitted sender) receiver=protection.outlook.com; client-ip=104.209.35.28; helo=us2.smtp.exclaimer.net; pr=C\nReceived: from us2.smtp.exclaimer.net (104.209.35.28) by AM4PEPF00027A61.mail.protection.outlook.com (10.167.16.70) with Microsoft SMTP Server (version=TLS1_2, cipher=TLS_ECDHE_RSA_WITH_AES_256_GCM_SHA384) id 15.20.8005.15 via Frontend Transport; Fri, 27 Sep 2024 08:45:16 +0000\nReceived: from EUR05-AM6-obe.outbound.protection.outlook.com (104.47.18.107)  by us2.smtp.exclaimer.net (104.209.35.28) with Exclaimer Signature Manager  ESMTP Proxy us2.smtp.exclaimer.net (tlsversion=TLS12,  tlscipher=TLS_DIFFIEHELLMAN_WITH_AES256_NONE); Fri, 27 Sep 2024 08:45:21  +0000\nX-ExclaimerHostedSignatures-MessageProcessed: true\nX-ExclaimerProxyLatency: 60754036\nX-ExclaimerImprintLatency: 6982960\nX-ExclaimerImprintAction: ffca50916c3947109bb41601c4838df6\nReceived: from GV1PR05MB9794.eurprd05.prod.outlook.com (2603:10a6:150:85::12) by PAXPR05MB7936.eurprd05.prod.outlook.com (2603:10a6:102:15b::20) with Microsoft SMTP Server (version=TLS1_2, cipher=TLS_ECDHE_RSA_WITH_AES_256_GCM_SHA384) id 15.20.7982.32; Fri, 27 Sep 2024 08:45:08 +0000\nReceived: from GV1PR05MB9794.eurprd05.prod.outlook.com ([fe80::5331:2c7c:519a:7a85]) by GV1PR05MB9794.eurprd05.prod.outlook.com ([fe80::5331:2c7c:519a:7a85%4]) with mapi id 15.20.7982.022; Fri, 27 Sep 2024 08:45:08 +0000\nFrom: Suha Abilmona <Suha.Abilmona@chalhoub.com>\nTo: Mohammed AL-AREQI <Mohammed.Al-areqi@chalhoub.com>, May Karaki <May.Karaki@chalhoub.com>, Joe Hobeika <Joe.Hobeika@chalhoub.com>, Hagop Ghazarian <Hagop.Ghazarian@chalhoub.com>, Gelynne Vargas <Gelynne.Vargas@chalhoub.com>\nCC: Grace Milan <Grace.Milan@chalhoub.com>, Mohammed El Neel <Mohammed.Elneel@chalhoub.com>\nSubject: RE: New Available Office Space 10 Floor AL Jazira Tower.",
      "start_pos": 0,
      "end_pos": 2824,
      "chunk_index": 0,
      "chunk_size": 2822,
      "metadata": {
        "doc_id": "C1ER4UL - new available office space 10 floor al jazira tower\\Headers\\C1ER4UL_08.txt",
        "doc_path": "C:\\Users\\ASUS\\Desktop\\Outlook\\C1ER4UL - new available office space 10 floor al jazira tower\\Headers\\C1ER4UL_08.txt"
      }
    },
    {
      "text": "nne Vargas <Gelynne.Vargas@chalhoub.com>\nCC: Grace Milan <Grace.Milan@chalhoub.com>, Mohammed El Neel <Mohammed.Elneel@chalhoub.com>\nSubject: RE: New Available Office Space 10 Floor AL Jazira Tower. \nThread-Topic: New Available Office Space 10 Floor AL Jazira Tower. \nThread-Index: AdrjLXfIvOLvQarERFq7NCtQmEoEDAbrtiCQACJourACNpW3EACNdTqQAMU2dRAABBh7QABr3jkgAAsRDOAAAAuSsAAAPgMjABreSpAAKDsRoAAJuPmw\nDate: Fri, 27 Sep 2024 08:45:05 +0000\nDeferred-Delivery: Fri, 27 Sep 2024 08:44:36 +0000\nMessage-ID: <GV1PR05MB97940CE21920365963FA01E8896B2@GV1PR05MB9794.eurprd05.prod.outlook.com>\nReferences: <GV1PR05MB9723215C83DA373D46240C6DC9B12@GV1PR05MB9723.eurprd05.prod.outlook.com> <GV1PR05MB9723210A369C1D0E25CF6CDEC99C2@GV1PR05MB9723.eurprd05.prod.outlook.com> <DX0P273MB09939B274D04D53E12603C5EEA9D2@DX0P273MB0993.AREP273.PROD.OUTLOOK.COM> <GV1PR05MB97239112BF9F3F8EFC351962C9602@GV1PR05MB9723.eurprd05.prod.outlook.com> <DX0P273MB099342260FDA14A1651B60EDEA632@DX0P273MB0993.AREP273.PROD.OUTLOOK.COM> <GV1PR05MB9723DD00FB783E9F76E484D3C96F2@GV1PR05MB9723.eurprd05.prod.outlook.com> <GV1PR05MB9794C6348B845DF94901602E89682@GV1PR05MB9794.eurprd05.prod.outlook.com> <GV1PR05MB9723EF31015CECC6590F6219C9692@GV1PR05MB9723.eurprd05.prod.outlook.com> <DU2PR05MB106859310B3311CA274C5EF24E3692@DU2PR05MB10685.eurprd05.prod.outlook.com> <DU2PR05MB106857061CDC84A7627B7A178E3692@DU2PR05MB10685.eurprd05.prod.outlook.com> <GV1PR05MB97232898E497A622123735C9C9692@GV1PR05MB9723.eurprd05.prod.outlook.com> <GV1PR05MB97944FC5703EB7C5A26554C7896A2@GV1PR05MB9794.eurprd05.prod.outlook.com> <GV1PR05MB9723DE85D044355D7A860EA8C96B2@GV1PR05MB9723.eurprd05.prod.outlook.com>\nIn-Reply-To: <GV1PR05MB9723DE85D044355D7A860EA8C96B2@GV1PR05MB9723.eurprd05.prod.outlook.com>\nAccept-Language: en-US\nContent-Language: en-US\nX-MS-Has-Attach: yes\nX-MS-TNEF-Correlator:",
      "start_pos": 2624,
      "end_pos": 4456,
      "chunk_index": 1,
      "chunk_size": 1831,
      "metadata": {
        "doc_id": "C1ER4UL - new available office space 10 floor al jazira tower\\Headers\\C1ER4UL_08.txt",
        "doc_path": "C:\\Users\\ASUS\\Desktop\\Outlook\\C1ER4UL - new available office space 10 floor al jazira tower\\Headers\\C1ER4UL_08.txt"
      }
    },
    {
      "text": "od.outlook.com>\nIn-Reply-To: <GV1PR05MB9723DE85D044355D7A860EA8C96B2@GV1PR05MB9723.eurprd05.prod.outlook.com>\nAccept-Language: en-US\nContent-Language: en-US\nX-MS-Has-Attach: yes\nX-MS-TNEF-Correlator:\nAuthentication-Results-Original: dkim=none (message not signed) header.d=none;dmarc=none action=none header.from=chalhoub.com;\nx-ms-traffictypediagnostic: GV1PR05MB9794:EE_|PAXPR05MB7936:EE_|AM4PEPF00027A61:EE_|VI0PR05MB11320:EE_|AS8PR05MB10824:EE_\nX-MS-Office365-Filtering-Correlation-Id: b701aa5f-d9b6-4ac6-649d-08dcded0b8e8\nX-MS-Exchange-AtpMessageProperties: SA|SL\nX-Microsoft-Antispam-Untrusted: BCL:0;ARA:13230040|366016|41050700001;\nX-Microsoft-Antispam-Message-Info-Original: nExzaTxQ0KsxYAl6kUCOxdaOb4K/utLTNlzzq+n+mkyUYTxvAnL+DvpKEI2vNrZoRaSWfpevIipZrmQK0UklRfn0LyH6AFOAdcHQ8Hig+/4r0Cttohw5b0evRBMNwDaJlalq/OIpKtcWSb2rYDgx3lz/J6U1i2dQm/NS9gEdu2c0HENP/d8G6oz9Bf/qz8qDt+IG8vEqWTIhqmn9hjm/5LKA7UVdq3NCFNSrCFr0yKcl9DX5BCjKf/jkaWUvR3x2dxV2IwF5zOJohUoZ5Qd0GaflFkAYaY4ydvCKTL+6DOmnl62xSs/Cr5edKSwBe7T6iTo4vNq3mPiJgLR4mFpu90Qo7Q6TXiWh8RLGVv5IhSRlFldMJRXsFUItOJOHxdF/74WxmbxkZ7pNcAkgtDmAcUaITe4/GSGrxyQx6j4YTwLTU32dOzcNKZAsqYidzD0l7IY7gZk1g8pECpWfwG/aBlMYIxH2gp7oSfFgDcq7kPy7XBTNSJkaw1SvXpK4b0upH8iqf+nFgaaeeGvd5rWl1kpGaiKN5b+FkFJrwMJ3ie45a+0qUJCO4T5EJvZFEsgzcAdtqEo0nurXRUKGqn3M3LmbqCyt4dvdEGKTLe67khPODtMRR6RAXrRHAHs9QTZ400C3oDTSbTh43w6D3LJ4aJg/qPShqMhwyPhYZ4L4zvW54SouqF0MymmjuBwTjnAApM8mAn+CC1uXe3A0DDx0xCslyvoAZHKrNZHXnfyJyMg6GD0Jeiu5/+XAkouancLK1A9gkuKJhUoQTzjd+sYqAA==\nX-Forefront-Antispam-Report-Untrusted: CIP:255.255.255.255;CTRY:;LANG:en;SCL:1;SRV:;IPV:NLI;SFV:NSPM;H:GV1PR05MB9794.eurprd05.prod.outlook.com;PTR:;CAT:NONE;SFS:(13230040)(366016)(41050700001);DIR:INT;\nContent-Type: multipart/mixed; boundary=\"_014_GV1PR05MB97940CE21920365963FA01E8896B2GV1PR05MB9794eurp_\"\nMIME-Version: 1.0\nX-MS-Exchange-Transport-CrossTenantHeadersStamped: PAXPR05MB7936\nX-OrganizationHeadersPreserved: PAXPR05MB7936.eurprd05.prod.outlook.com\nReturn-Path: Suha.Abilmona@chalhoub.com\nX-MS-Exchange-Organization-ExpirationStartTime: 27 Sep 2024 08:45:21.6569 (UTC)\nX-MS-Exchange-Organization-ExpirationStartTimeReason: OriginalSubmit\nX-MS-Exchange-Organization-ExpirationInterval: 1:00:00:00.0000000\nX-MS-Exchange-Organization-ExpirationIntervalReason: OriginalSubmit\nX-MS-Exchange-Organization-Network-Message-Id: b701aa5f-d9b6-4ac6-649d-08dcded0b8e8\nX-EOPAttributedMessage: 0\nX-MS-Exchange-Organization-MessageDirectionality: Originating\nX-MS-Exchange-Organization-AuthAs: Internal\nX-MS-Exchange-Organization-AuthMechanism: 04\nX-MS-Exchange-Organization-AuthSource: GV1PR05MB9794.eurprd05.prod.outlook.com\nX-MS-Exchange-Organization-SCL: 1\nX-CrossPremisesHeadersPromoted: AM4PEPF00027A61.eurprd04.prod.outlook.com\nX-CrossPremisesHeadersFiltered: AM4PEPF00027A61.eurprd04.prod.outlook.com\nX-MS-Exchange-Transport-CrossTenantHeadersStripped: AM4PEPF00027A61.eurprd04.prod.outlook.com\nX-MS-PublicTrafficType: Email\nX-OriginatorOrg: AMSQ4STQ75H8S1R330DGE41C1M.smtp.exclaimer.cloud\nX-MS-Office365-Filtering-Correlation-Id-Prvs: 95d1333d-6496-4b5a-642c-08dcded0b0b5\nX-Microsoft-Antispam: BCL:0;ARA:13230040|366016|35042699022|82310400026|41050700001;\nX-Forefront-Antispam-Report: CIP:104.209.35.28;CTRY:US;LANG:en;SCL:1;SRV:;IPV:CAL;SFV:NSPM;H:us2.smtp.exclaimer.net;PTR:us2.smtp.exclaimer.net;CAT:NONE;SFS:(13230040)(366016)(35042699022)(82310400026)(41050700001);DIR:INT;\nX-MS-Exchange-CrossTenant-OriginalArrivalTime: 27 Sep 2024 08:45:16.7663 (UTC)\nX-MS-Exchange-CrossTenant-Network-Message-Id: b701aa5f-d9b6-4ac6-649d-08dcded0b8e8\nX-MS-Exchange-CrossTenant-Id: 6ef8304c-f37b-42a5-a569-0a7d8249fbf3\nX-MS-Exchange-CrossTenant-OriginalAttributedTenantConnectingIp: TenantId=6ef8304c-f37b-42a5-a569-0a7d8249fbf3;Ip=[104.209.35.28];Helo=[us2.smtp.exclaimer.net]\nX-MS-Exchange-CrossTenant-AuthAs: Internal\nX-MS-Exchange-CrossTenant-AuthSource: GV1PR05MB9794.eurprd05.prod.outlook.com\nX-MS-Exchange-CrossTenant-FromEntityHeader: HybridOnPrem\nX-MS-Exchange-Transport-CrossTenantHeadersStamped: VI0PR05MB11320\nX-MS-Exchange-Transport-EndToEndLatency: 00:03:29.4939108\nX-MS-Exchange-Processed-By-BccFoldering: 15.20.7982.022\nX-Microsoft-Antispam-Mailbox-Delivery: rwl:1;ucf:0;jmr:0;auth:0;dest:I;ENG:(910001)(944506478)(944626604)(920097)(815096)(255002)(410001)(930097)(140003)(1420198);\nX-Microsoft-Antispam-Message-Info: =?us-ascii?Q?DvfX51W4sypbWzpv8mlRxr2DiYvUQkD0NgguaruDHTHXiCX4BP8iWmvJ9qF+?= =?us-ascii?Q?HweBEUd20+OB05j5b32+8WR+/fsYlyy38jerFI90Fnq6IEhEUW1zqp6bLYP/?= =?us-ascii?Q?hh/NWX4giTCGbLAvQJnfWxNtMaExGCHYTKnqdp5/RvkWIq0J72j7wJ/86xJP?= =?us-ascii?Q?yfkMOSomPY/I1xbdYeievJdAniYJb+jVcs6iFCCkztjemQiGUhxo+xDkS6IU?= =?us-ascii?Q?BK5w27VQg+qj1CM0bAnw1cN10D7b3nKWg680gjy90US9HXjbJ99S0kn0GTwM?= =?us-ascii?Q?3JkhovpzE3njUCIPtw5yh+WaPNKlcxTqldW4vVFePicgioSB6ffErWBJxTAc?= =?us-ascii?Q?e2YFJvbr2MYLlBjV6dLbFhP3wohLOWZ7f3zCVt7VtfBuTg/0nL467x1dop0P?= =?us-ascii?Q?2CzsBzAu4iGuFizAoQfxVfT/FCxKyyi4IlaeGMLv97OzYlMwKorRv3xiakI7?= =?us-ascii?Q?lfZFWX8spk7Q2cfTttkGS65bQ8ikcmKjM82Aum8vbfu+ZqNAdwu+z6HGduNJ?= =?us-ascii?Q?SyRtVGbGYqjQm3CYnZ4Vgqn2TuywffosuWh0oDmRYU2eAS3CpDz5DoPYlspQ?= =?us-ascii?Q?5nK0RU1n/jJOBXZyN57RcGYTsBbZGSIGpLkaji+hwTZwz1xpMhAFqP+A0kZr?= =?us-ascii?Q?wvTlGF5yjnc9GqtALlUw/siA1iKnGm2O+ziJviFBrBdaKX+zd5vQNsh0Fb0r?= =?us-ascii?Q?t3K3bWmMNqmoD2x4DlzVE1aaotcbQMr8poW0/zJg+TREkF4evwx9xPQ/OV4x?= =?us-ascii?Q?juVaDo9CKeC5LkUOS7OEx4lDTeaA77B2MdTBD+OGRD7JoyvU7TFlkmHqvZRT?= =?us-ascii?Q?C38wlna4EZE/rBrgVXYkvRVsYUoSJrmgP4pKjAhEfTJWBfVDCqEyHptz7qth?= =?us-ascii?Q?Z31CMoyi0DUbSbA8L6LQcU4GDTEqnUxTxXsgcVJynyE47ri86NhVuvifPbu7?= =?us-ascii?Q?p9nHnlf0Vd4xBG8c/ge7MFDVbZyuE159AwQxfZopKfXeUdMZkDMB7dBObj6g?= =?us-ascii?Q?JpQ3?=",
      "start_pos": 4256,
      "end_pos": 9875,
      "chunk_index": 2,
      "chunk_size": 5619,
      "metadata": {
        "doc_id": "C1ER4UL - new available office space 10 floor al jazira tower\\Headers\\C1ER4UL_08.txt",
        "doc_path": "C:\\Users\\ASUS\\Desktop\\Outlook\\C1ER4UL - new available office space 10 floor al jazira tower\\Headers\\C1ER4UL_08.txt"
      }
    }
  ],
  "metadata": {
    "chunked_at": "2025-10-06T06:28:04.874798",
    "chunk_config": {
      "chunk_size": 1600,
      "chunk_overlap": 200,
      "min_chunk_size": 100,
      "respect_sentences": true,
      "respect_paragraphs": true,
      "base_max_chunks": 25,
      "progressive_scaling": true
    },
    "original_size": 9950
  }
}