{
  "doc_id": "C1ER4UL - new available office space 10 floor al jazira tower\\Headers\\C1ER4UL_18.txt",
  "doc_path": "C:\\Users\\ASUS\\Desktop\\Outlook\\C1ER4UL - new available office space 10 floor al jazira tower\\Headers\\C1ER4UL_18.txt",
  "num_chunks": 3,
  "chunks": [
    {
      "text": "Received: from DU2PR05MB10647.eurprd05.prod.outlook.com (2603:10a6:10:495::15) by VI1PR05MB10819.eurprd05.prod.outlook.com with HTTPS; Mon, 14 Oct 2024 11:43:21 +0000\nReceived: from AS9PR06CA0406.eurprd06.prod.outlook.com (2603:10a6:20b:461::16) by DU2PR05MB10647.eurprd05.prod.outlook.com (2603:10a6:10:495::15) with Microsoft SMTP Server (version=TLS1_2, cipher=TLS_ECDHE_RSA_WITH_AES_256_GCM_SHA384) id 15.20.7982.32; Mon, 14 Oct 2024 11:43:13 +0000\nReceived: from AMS0EPF00000195.eurprd05.prod.outlook.com (2603:10a6:20b:461:cafe::78) by AS9PR06CA0406.outlook.office365.com (2603:10a6:20b:461::16) with Microsoft SMTP Server (version=TLS1_2, cipher=TLS_ECDHE_RSA_WITH_AES_256_GCM_SHA384) id 15.20.8048.24 via Frontend Transport; Mon, 14 Oct 2024 11:43:13 +0000\nAuthentication-Results: spf=pass (sender IP is 104.209.35.28) smtp.mailfrom=chalhoub.com; dkim=none (message not signed) header.d=none;dmarc=pass action=none header.from=chalhoub.com;\nReceived-SPF: Pass (protection.outlook.com: domain of chalhoub.com designates 104.209.35.28 as permitted sender) receiver=protection.outlook.com; client-ip=104.209.35.28; helo=us2.smtp.exclaimer.net; pr=C\nReceived: from us2.smtp.exclaimer.net (104.209.35.28) by AMS0EPF00000195.mail.protection.outlook.com (10.167.16.215) with Microsoft SMTP Server (version=TLS1_2, cipher=TLS_ECDHE_RSA_WITH_AES_256_GCM_SHA384) id 15.20.7918.13 via Frontend Transport; Mon, 14 Oct 2024 11:43:09 +0000\nReceived: from EUR03-VI1-obe.outbound.protection.outlook.com (104.47.30.113)  by us2.smtp.exclaimer.net (104.209.35.28) with Exclaimer Signature Manager  ESMTP Proxy us2.smtp.exclaimer.net (tlsversion=TLS12,  tlscipher=TLS_DIFFIEHELLMAN_WITH_AES256_NONE); Mon, 14 Oct 2024 11:43:12  +0000\nX-ExclaimerHostedSignatures-MessageProcessed: true\nX-ExclaimerProxyLatency: 55529001\nX-ExclaimerImprintLatency: 6995929\nX-ExclaimerImprintAction: b7e98aa1a3aa425b9824d22ffa7f0ff7\nReceived: from GV1PR05MB9723.eurprd05.prod.outlook.com (2603:10a6:150:a0::21) by AS8PR05MB9761.eurprd05.prod.outlook.com (2603:10a6:20b:537::15) with Microsoft SMTP Server (version=TLS1_2, cipher=TLS_ECDHE_RSA_WITH_AES_256_GCM_SHA384) id 15.20.7982.34; Mon, 14 Oct 2024 11:42:55 +0000\nReceived: from GV1PR05MB9723.eurprd05.prod.outlook.com ([fe80::e62e:2a82:13b8:245e]) by GV1PR05MB9723.eurprd05.prod.outlook.com ([fe80::e62e:2a82:13b8:245e%5]) with mapi id 15.20.7982.033; Mon, 14 Oct 2024 11:42:54 +0000\nFrom: Mohammed AL-AREQI <Mohammed.Al-areqi@chalhoub.com>\nTo: Suha Abilmona <Suha.Abilmona@chalhoub.com>, Joe Hobeika <Joe.Hobeika@chalhoub.com>\nCC: Grace Milan <Grace.Milan@chalhoub.com>, Mohammed El Neel <Mohammed.Elneel@chalhoub.com>, May Karaki <May.Karaki@chalhoub.com>, Hagop Ghazarian <Hagop.Ghazarian@chalhoub.com>, Gelynne Vargas <Gelynne.Vargas@chalhoub.com>, Rose Corpuz <Rose.Corpuz@chalhoub.com>, Celine Kibrit <Celine.Kibrit@chalhoub.com>\nSubject: RE: New Available Office Space 10 Floor AL Jazira Tower.",
      "start_pos": 0,
      "end_pos": 2927,
      "chunk_index": 0,
      "chunk_size": 2925,
      "metadata": {
        "doc_id": "C1ER4UL - new available office space 10 floor al jazira tower\\Headers\\C1ER4UL_18.txt",
        "doc_path": "C:\\Users\\ASUS\\Desktop\\Outlook\\C1ER4UL - new available office space 10 floor al jazira tower\\Headers\\C1ER4UL_18.txt"
      }
    },
    {
      "text": "m>, Gelynne Vargas <Gelynne.Vargas@chalhoub.com>, Rose Corpuz <Rose.Corpuz@chalhoub.com>, Celine Kibrit <Celine.Kibrit@chalhoub.com>\nSubject: RE: New Available Office Space 10 Floor AL Jazira Tower. \nThread-Topic: New Available Office Space 10 Floor AL Jazira Tower. \nThread-Index: AdrjLXfIvOLvQarERFq7NCtQmEoEDAbrtiCQACJourACNpW3EACNdTqQAMU2dRAABBh7QABr3jkgAAsRDOAAAAuSsAAAPgMjABreSpAAKDsRoAAJuPmwAKHL5pAAAMNHoABl3JCgAAD1LnAAJARbwAGTUBfgAJ7xwqAAAIvn0A==\nDate: Mon, 14 Oct 2024 11:42:54 +0000\nMessage-ID: <GV1PR05MB9723D714746BD62078BD39C6C9442@GV1PR05MB9723.eurprd05.prod.outlook.com>\nReferences: <GV1PR05MB9723215C83DA373D46240C6DC9B12@GV1PR05MB9723.eurprd05.prod.outlook.com> <GV1PR05MB9723210A369C1D0E25CF6CDEC99C2@GV1PR05MB9723.eurprd05.prod.outlook.com> <DX0P273MB09939B274D04D53E12603C5EEA9D2@DX0P273MB0993.AREP273.PROD.OUTLOOK.COM> <GV1PR05MB97239112BF9F3F8EFC351962C9602@GV1PR05MB9723.eurprd05.prod.outlook.com> <DX0P273MB099342260FDA14A1651B60EDEA632@DX0P273MB0993.AREP273.PROD.OUTLOOK.COM> <GV1PR05MB9723DD00FB783E9F76E484D3C96F2@GV1PR05MB9723.eurprd05.prod.outlook.com> <GV1PR05MB9794C6348B845DF94901602E89682@GV1PR05MB9794.eurprd05.prod.outlook.com> <GV1PR05MB9723EF31015CECC6590F6219C9692@GV1PR05MB9723.eurprd05.prod.outlook.com> <DU2PR05MB106859310B3311CA274C5EF24E3692@DU2PR05MB10685.eurprd05.prod.outlook.com> <DU2PR05MB106857061CDC84A7627B7A178E3692@DU2PR05MB10685.eurprd05.prod.outlook.com> <GV1PR05MB97232898E497A622123735C9C9692@GV1PR05MB9723.eurprd05.prod.outlook.com> <GV1PR05MB97944FC5703EB7C5A26554C7896A2@GV1PR05MB9794.eurprd05.prod.outlook.com> <GV1PR05MB9723DE85D044355D7A860EA8C96B2@GV1PR05MB9723.eurprd05.prod.outlook.com> <GV1PR05MB97940CE21920365963FA01E8896B2@GV1PR05MB9794.eurprd05.prod.outlook.com> <GV1PR05MB9723B2931871586FD52BD308C9762@GV1PR05MB9723.eurprd05.prod.outlook.com> <GV1PR05MB9794E19D1E9F091FB5AF90A589762@GV1PR05MB9794.eurprd05.prod.outlook.com> <GV1PR05MB9723349BABC9FCA458C272BCC9702@GV1PR05MB9723.eurprd05.prod.outlook.com> <GV1PR05MB97940B3F5BC6BA43339EA48489702@GV1PR05MB9794.eurprd05.prod.outlook.com> <GV1PR05MB972306FF4D47CDD628C9F417C9712@GV1PR05MB9723.eurprd05.prod.outlook.com> <GV1PR05MB9794D36EEC3743F01AC1CD5989792@GV1PR05MB9794.eurprd05.prod.outlook.com> <GV1PR05MB9794B93F2A94A1C5F17BCCEC89442@GV1PR05MB9794.eurprd05.prod.outlook.com>\nIn-Reply-To: <GV1PR05MB9794B93F2A94A1C5F17BCCEC89442@GV1PR05MB9794.eurprd05.prod.outlook.com>\nAccept-Language: en-GB, en-US\nContent-Language: en-US\nX-Mentions: Joe.Hobeika@chalhoub.com\nX-MS-Has-Attach: yes\nX-MS-TNEF-Correlator:",
      "start_pos": 2727,
      "end_pos": 5256,
      "chunk_index": 1,
      "chunk_size": 2528,
      "metadata": {
        "doc_id": "C1ER4UL - new available office space 10 floor al jazira tower\\Headers\\C1ER4UL_18.txt",
        "doc_path": "C:\\Users\\ASUS\\Desktop\\Outlook\\C1ER4UL - new available office space 10 floor al jazira tower\\Headers\\C1ER4UL_18.txt"
      }
    },
    {
      "text": "93F2A94A1C5F17BCCEC89442@GV1PR05MB9794.eurprd05.prod.outlook.com>\nAccept-Language: en-GB, en-US\nContent-Language: en-US\nX-Mentions: Joe.Hobeika@chalhoub.com\nX-MS-Has-Attach: yes\nX-MS-TNEF-Correlator:\nAuthentication-Results-Original: dkim=none (message not signed) header.d=none;dmarc=none action=none header.from=chalhoub.com;\nx-ms-traffictypediagnostic: GV1PR05MB9723:EE_|AS8PR05MB9761:EE_|AMS0EPF00000195:EE_|DU2PR05MB10647:EE_|VI1PR05MB10819:EE_\nX-MS-Office365-Filtering-Correlation-Id: 9a78a5b4-6515-492e-0f79-08dcec45628a\nX-MS-Exchange-AtpMessageProperties: SA|SL\nX-Microsoft-Antispam-Untrusted: BCL:0;ARA:13230040|366016|41050700001;\nX-Microsoft-Antispam-Message-Info-Original: zZhbgRFvYP0dsMgwdnzktiBVNXs+A5tok5+MPYaueK9Xxo1z6JHa2z8GwbRCmG2bI269VFIFTszK2Kq1oR64LoNvk5XeH3UtvIKvgQy66Dz2Ep6m9t7Xr5L1MeNXlFk9Qwm+Zj8VxX09uhciMkVsGx6zK3bozu+8cLsl+ZstFFH0MKQShCZdE8oectpj5Xevp3+7qQzeGOxUCa/Eaav82QpmU8JesKfuyU1Y+IOimHgjEzIrIhoLkpkUSsTG0rjR+aRe8GtCimjzzrrH0R2TXUP4K09rrKfQpCPVAi60RSfflKmx7dI2nGGeEyRtl6gEOmMZQ602lJJ9rtX21iqaqHL1iWdi3b6DgtUDXa101Pvb/902+KviVvYoOhc5DOVToedvWDNY9+GkWkDXvsjhEmVsDr67KdC9YrQR+aivuRdWQhC6mKkdU6GEEB3GUO7vb7B0/hHTyY+6uuhT42BiytfMwEgxJvBpwE6CKlVpWnOae0ficGfAGQpOa37jibPRkYVNA+J1cIB6jM1R9hRwdYYRKm9peeImPNzWSmwJw/Vgdyh+HbTbHmMazj0eYGuAo+9nvKT3RP0EQSQDYgy9j+VMnycIvoFpcnKuvQgzxLUh981W9sM3q0bbUL9sOKG55qJosxT2HIj9X6WN7kWvuvO55mkdOpK6dN8azBeOVUc+rXeM6icrrCqNTIc7GZJsuvyobzO6iWVH2nDQG7QKe3ErGFaiBh/lQ57Uu8biDQKMhbZHXakkmOWr9NZAVp7e3ki6h/DyTS2XwAMZyZzoOA==\nX-Forefront-Antispam-Report-Untrusted: CIP:255.255.255.255;CTRY:;LANG:en;SCL:1;SRV:;IPV:NLI;SFV:NSPM;H:GV1PR05MB9723.eurprd05.prod.outlook.com;PTR:;CAT:NONE;SFS:(13230040)(366016)(41050700001);DIR:INT;\nContent-Type: multipart/related; boundary=\"_010_GV1PR05MB9723D714746BD62078BD39C6C9442GV1PR05MB9723eurp_\"; type=\"multipart/alternative\"\nMIME-Version: 1.0\nX-MS-Exchange-Transport-CrossTenantHeadersStamped: AS8PR05MB9761\nX-OrganizationHeadersPreserved: AS8PR05MB9761.eurprd05.prod.outlook.com\nReturn-Path: Mohammed.Al-areqi@chalhoub.com\nX-MS-Exchange-Organization-ExpirationStartTime: 14 Oct 2024 11:43:12.9881 (UTC)\nX-MS-Exchange-Organization-ExpirationStartTimeReason: OriginalSubmit\nX-MS-Exchange-Organization-ExpirationInterval: 1:00:00:00.0000000\nX-MS-Exchange-Organization-ExpirationIntervalReason: OriginalSubmit\nX-MS-Exchange-Organization-Network-Message-Id: 9a78a5b4-6515-492e-0f79-08dcec45628a\nX-EOPAttributedMessage: 0\nX-MS-Exchange-Organization-MessageDirectionality: Originating\nX-MS-Exchange-Organization-AuthAs: Internal\nX-MS-Exchange-Organization-AuthMechanism: 04\nX-MS-Exchange-Organization-AuthSource: GV1PR05MB9723.eurprd05.prod.outlook.com\nX-MS-Exchange-Organization-SCL: 1\nX-CrossPremisesHeadersPromoted: AMS0EPF00000195.eurprd05.prod.outlook.com\nX-CrossPremisesHeadersFiltered: AMS0EPF00000195.eurprd05.prod.outlook.com\nX-MS-Exchange-Transport-CrossTenantHeadersStripped: AMS0EPF00000195.eurprd05.prod.outlook.com\nX-MS-PublicTrafficType: Email\nX-OriginatorOrg: AMSQ4STQ75H8S1R330DGE41C1M.smtp.exclaimer.cloud\nX-MS-Office365-Filtering-Correlation-Id-Prvs: 6df34e42-6213-4457-4b7b-08dcec4557ac\nX-Microsoft-Antispam: BCL:0;ARA:13230040|366016|35042699022|82310400026|41050700001;\nX-Forefront-Antispam-Report: CIP:104.209.35.28;CTRY:US;LANG:en;SCL:1;SRV:;IPV:CAL;SFV:NSPM;H:us2.smtp.exclaimer.net;PTR:us2.smtp.exclaimer.net;CAT:NONE;SFS:(13230040)(366016)(35042699022)(82310400026)(41050700001);DIR:INT;\nX-MS-Exchange-CrossTenant-OriginalArrivalTime: 14 Oct 2024 11:43:09.0350 (UTC)\nX-MS-Exchange-CrossTenant-Network-Message-Id: 9a78a5b4-6515-492e-0f79-08dcec45628a\nX-MS-Exchange-CrossTenant-Id: 6ef8304c-f37b-42a5-a569-0a7d8249fbf3\nX-MS-Exchange-CrossTenant-OriginalAttributedTenantConnectingIp: TenantId=6ef8304c-f37b-42a5-a569-0a7d8249fbf3;Ip=[104.209.35.28];Helo=[us2.smtp.exclaimer.net]\nX-MS-Exchange-CrossTenant-AuthAs: Internal\nX-MS-Exchange-CrossTenant-AuthSource: GV1PR05MB9723.eurprd05.prod.outlook.com\nX-MS-Exchange-CrossTenant-FromEntityHeader: HybridOnPrem\nX-MS-Exchange-Transport-CrossTenantHeadersStamped: DU2PR05MB10647\nX-MS-Exchange-Transport-EndToEndLatency: 00:00:12.5358926\nX-MS-Exchange-Processed-By-BccFoldering: 15.20.7982.032\nX-Microsoft-Antispam-Mailbox-Delivery: rwl:1;ucf:0;jmr:0;auth:0;dest:I;ENG:(910001)(944506478)(944626604)(920097)(815096)(255002)(410001)(930097)(140003)(1420198);\nX-Microsoft-Antispam-Message-Info: =?us-ascii?Q?+PkyoI4ClWNEbmgd822ysjnFhO15LD1eUuubUeggrcbojeDGvBzwsMJv3zMD?= =?us-ascii?Q?tOVbWJUoBRuY9Ze+cxEctcPC6HrSm1Fvps/2a4DU1hVp84DReXHZ2xM4w53W?= =?us-ascii?Q?cp2yWkLzNN2IR0fesWgJ6kwzg18nugQhS8Jv2onoCyDX60f/UvylSfEcBSG9?= =?us-ascii?Q?PhZ+qZzze+l2VVhIfTN0vLM7AqMwGI+xTffdVtZywI801e7irEfaYsrh/JiJ?= =?us-ascii?Q?XD7tGb82XZXR1z+WW0ClB0j54o6+hbywBh+pVXT0RzFgdg/W9k8j50WHm6aa?= =?us-ascii?Q?UejuNSmVyvJV2v2Vrk2alAUDSktnjiltm37nEJDgQyezqDI4m3+P6QXUy52d?= =?us-ascii?Q?E7JKqjmHZbt5XDq2tIiyhoIHps4Od3pWHooPG9z/aPa9BsI02Ztm16RAB8ES?= =?us-ascii?Q?u9Zxa8ZOOpkt/rvQgc/w0Aqqx3b+2EcJ7ZbXmAnz8oVwB1pLgjJj0VGS6dpQ?= =?us-ascii?Q?OV4gYkiwvyIeVzcvuTMm8vvdrPMQQkKTMp/wYYX0yM7puZCUhj0uRZuLdm0l?= =?us-ascii?Q?riOnx4nG9rwSKNQC8nDoItWfM/pwzfw6Vgu2QX4Dfx7lMSOIiLeTv+jg/fFX?= =?us-ascii?Q?0pICfEVvryiysIOfqp3WRPLzYGXHapqc1Rds52oeDr8IbpVpZW+iZJuDGCTq?= =?us-ascii?Q?2OMOP8Ml0LLI2txxjYJ90md9A8Qofiseh7BzR6aqAIb457satSqqzVRtmq9k?= =?us-ascii?Q?GMR34hI9Q27GLoO8Jomb/Lz+ROHmrqNS1DYwzvcJ3V1xdNF1g3bgV1L1u8eN?= =?us-ascii?Q?CPRqunOr/sKjrLDRWnaydtI2FfrrZ0Fc5MgSwRdZi0FakLxrgx8yhjm+aQ2Y?= =?us-ascii?Q?kFUARlbzj5WVY265aJn2u3EyGXK7CI8/8Z7KEuR/23a6Ilkj7qFot/ZEeVhx?= =?us-ascii?Q?JCHIsqUGe1IpqiTZT2Qs1L+rVVYG2KZIHwSEGKoo2OIsrPlFHGgqTNWconp+?= =?us-ascii?Q?oUJ0ZHRlou19pM4tulyN6plI9F+P4mMa+kgpICgkhj0CjbaZa7SUG7xlOMDf?= =?us-ascii?Q?94Rg?=",
      "start_pos": 5056,
      "end_pos": 10711,
      "chunk_index": 2,
      "chunk_size": 5655,
      "metadata": {
        "doc_id": "C1ER4UL - new available office space 10 floor al jazira tower\\Headers\\C1ER4UL_18.txt",
        "doc_path": "C:\\Users\\ASUS\\Desktop\\Outlook\\C1ER4UL - new available office space 10 floor al jazira tower\\Headers\\C1ER4UL_18.txt"
      }
    }
  ],
  "metadata": {
    "chunked_at": "2025-10-06T06:26:49.646847",
    "chunk_config": {
      "chunk_size": 1600,
      "chunk_overlap": 200,
      "min_chunk_size": 100,
      "respect_sentences": true,
      "respect_paragraphs": true,
      "base_max_chunks": 25,
      "progressive_scaling": true
    },
    "original_size": 10786
  }
}