{
  "doc_id": "C1UKO3Y - theft incident in stores\\Headers\\C1UKO3Y_03.txt",
  "doc_path": "C:\\Users\\ASUS\\Desktop\\Outlook\\C1UKO3Y - theft incident in stores\\Headers\\C1UKO3Y_03.txt",
  "num_chunks": 2,
  "chunks": [
    {
      "text": "Received: from PAVPR05MB10022.eurprd05.prod.outlook.com (2603:10a6:102:32c::10) by AS8PR05MB10824.eurprd05.prod.outlook.com with HTTPS; Mon, 7 Oct 2024 13:09:12 +0000\nReceived: from DUZPR01CA0127.eurprd01.prod.exchangelabs.com (2603:10a6:10:4bc::13) by PAVPR05MB10022.eurprd05.prod.outlook.com (2603:10a6:102:32c::10) with Microsoft SMTP Server (version=TLS1_2, cipher=TLS_ECDHE_RSA_WITH_AES_256_GCM_SHA384) id 15.20.7982.34; Mon, 7 Oct 2024 13:09:04 +0000\nReceived: from DU2PEPF00028D12.eurprd03.prod.outlook.com (2603:10a6:10:4bc:cafe::95) by DUZPR01CA0127.outlook.office365.com (2603:10a6:10:4bc::13) with Microsoft SMTP Server (version=TLS1_2, cipher=TLS_ECDHE_RSA_WITH_AES_256_GCM_SHA384) id 15.20.8026.21 via Frontend Transport; Mon, 7 Oct 2024 13:09:04 +0000\nAuthentication-Results: spf=pass (sender IP is 185.58.86.160) smtp.mailfrom=etoilegroup.com; dkim=pass (signature was verified) header.d=etoilegroup.com;dmarc=pass action=none header.from=etoilegroup.com;compauth=pass reason=100\nReceived-SPF: Pass (protection.outlook.com: domain of etoilegroup.com designates 185.58.86.160 as permitted sender) receiver=protection.outlook.com; client-ip=185.58.86.160; helo=eu-smtp-delivery-160.mimecast.com; pr=C\nReceived: from eu-smtp-delivery-160.mimecast.com (185.58.86.160) by DU2PEPF00028D12.mail.protection.outlook.com (10.167.242.26) with Microsoft SMTP Server (version=TLS1_3, cipher=TLS_AES_256_GCM_SHA384) id 15.20.8048.13 via Frontend Transport; Mon, 7 Oct 2024 13:09:03 +0000\nDKIM-Signature: v=1; a=rsa-sha256; c=relaxed/relaxed; d=etoilegroup.com; s=mimecast20220523; t=1728306543; h=from:from:reply-to:subject:subject:date:date:message-id:message-id:  to:to:cc:cc:mime-version:mime-version:content-type:content-type:  in-reply-to:in-reply-to:references:references; bh=QlOp9wKRdVh2sr/xislPX5z/ACxzgD7gVQXXAf0UvU4=; b=ZtR3yIAXs5WzkmS5fVlGeSEAhc8AdNfCmkmCKkY6CD+v/2KhWOKHe5wE5QUDBIEhRM0tr6 4gk+iSMY9S1DwHF/CXR5gRcZqcqVCXrrKQWK1YT7GMvr9r0T1ahO+apPKl03ps2xTX5Bzt zW24wOFUSlIz6Hs4/9JykzZbCBj4R96ly10mNqhI1Ss2fBHDF8QezCw3dQ7IwHuqH07wlW AwJB5hn5M0mZcW3n26E2LrK5wejuQO1oZlxSYQEG5dxf5oukQvO9vQHEG8PmvU727fQmSi zTlqdE0Q4cWrY9bz13OFVRuJs3Wl0exjN7iSAP4/UO8JbWSQqZfZWMn2tKWLqQ==\nReceived: from EUR05-AM6-obe.outbound.protection.outlook.com (mail-am6eur05lp2105.outbound.protection.outlook.com [104.47.18.105]) by relay.mimecast.com with ESMTP with STARTTLS (version=TLSv1.2, cipher=TLS_ECDHE_RSA_WITH_AES_256_GCM_SHA384) id uk-mta-51-w4FYU5y9NRm9iIvI1JxZmQ-1; Mon, 07 Oct 2024 14:09:00 +0100\nX-MC-Unique: w4FYU5y9NRm9iIvI1JxZmQ-1\nReceived: from PAXPR09MB5021.eurprd09.prod.outlook.com (2603:10a6:102:13c::12) by VI0PR09MB7389.eurprd09.prod.outlook.com (2603:10a6:800:23c::15) with Microsoft SMTP Server (version=TLS1_2, cipher=TLS_ECDHE_RSA_WITH_AES_256_GCM_SHA384) id 15.20.8026.22; Mon, 7 Oct 2024 13:08:54 +0000\nReceived: from PAXPR09MB5021.eurprd09.prod.outlook.com ([fe80::a841:959e:30bf:ebe]) by PAXPR09MB5021.eurprd09.prod.outlook.com ([fe80::a841:959e:30bf:ebe%7]) with mapi id 15.20.8026.020; Mon, 7 Oct 2024 13:08:54 +0000\nFrom: Roselle Reyes <Roselle.Reyes@etoilegroup.com>\nTo: Hagop Ghazarian <Hagop.Ghazarian@chalhoub.com>\nCC: Ralph Joudet <Ralph.Joudet@etoilegroup.com>\nSubject: RE: Theft incident in stores\nThread-Topic: Theft incident in stores\nThread-Index: AdsYgAIa/2a+azqsTK22+uwGnn9UZAAODiLMAAAmGbA=\nDate: Mon, 7 Oct 2024 13:08:54 +0000\nMessage-ID: <PAXPR09MB5021E1E1037A109F975F4D0CEC7D2@PAXPR09MB5021.eurprd09.prod.outlook.com>\nReferences: <PAXPR09MB5021E58B1E67665BBFF11B0AEC7D2@PAXPR09MB5021.eurprd09.prod.outlook.com> <AS8PR05MB108246083A46699BC360E905B9D7D2@AS8PR05MB10824.eurprd05.prod.outlook.com>\nIn-Reply-To: <AS8PR05MB108246083A46699BC360E905B9D7D2@AS8PR05MB10824.eurprd05.prod.outlook.com>\nAccept-Language: en-US\nX-MS-Has-Attach: yes\nX-MS-TNEF-Correlator:",
      "start_pos": 0,
      "end_pos": 3789,
      "chunk_index": 0,
      "chunk_size": 3788,
      "metadata": {
        "doc_id": "C1UKO3Y - theft incident in stores\\Headers\\C1UKO3Y_03.txt",
        "doc_path": "C:\\Users\\ASUS\\Desktop\\Outlook\\C1UKO3Y - theft incident in stores\\Headers\\C1UKO3Y_03.txt"
      }
    },
    {
      "text": "R05MB10824.eurprd05.prod.outlook.com>\nIn-Reply-To: <AS8PR05MB108246083A46699BC360E905B9D7D2@AS8PR05MB10824.eurprd05.prod.outlook.com>\nAccept-Language: en-US\nX-MS-Has-Attach: yes\nX-MS-TNEF-Correlator:\nmsip_labels:\nx-ms-traffictypediagnostic: PAXPR09MB5021:EE_|VI0PR09MB7389:EE_|DU2PEPF00028D12:EE_|PAVPR05MB10022:EE_|AS8PR05MB10824:EE_\nX-MS-Office365-Filtering-Correlation-Id: 2e722fee-31e6-4675-d0f5-08dce6d137e0\nx-ld-processed: c1e088ff-740e-4b14-b383-a2cd47556146,ExtAddr\nx-ms-exchange-senderadcheck: 1\nx-ms-exchange-antispam-relay: 0\nX-Microsoft-Antispam-Untrusted: BCL:0;ARA:13230040|366016|1800799024|376014|38070700018\nX-Microsoft-Antispam-Message-Info-Original: =?us-ascii?Q?NNM2Ce+xGTwbtqMXYNsvLI3mMAZKtDqLylBCd8J7q0PBYQxIkNM34reyyZ9d?= =?us-ascii?Q?cNyjnPNWL9+AnDw74d5Ahz5bP4IMYL7FxCOYdrWY0sg1T9El2c/04Mp/7tIb?= =?us-ascii?Q?p0ZcybHw8paOHG5z3orJEshSWWOrCialOG/yOMENrM/hziUKCIqsBDr2WAMn?= =?us-ascii?Q?0IPyMXQfW/7wdFmQ5+TonWNwVP5JlPmBYYCAiNN+VRtEc4F/DZfx/t86R6EX?= =?us-ascii?Q?FvgAvnva0RlF79/u+kDylnNOU2H8MDq1CwQIMKMOV7+szhjDFmDesrp9Jf5k?= =?us-ascii?Q?OuN+27gqVN+Ow3rVu/3mkaZlB/3TbNZb0vQjvisE6AJZSWTDofWZXxG/+rgt?= =?us-ascii?Q?yBaD6o4TA1nXVaY4nrxl/Qz+t3KkHB/aLs2dQdYSOAdCx1EQOPVSyxZMg31W?= =?us-ascii?Q?2S3Y9w645xT+g7ZzqIp+4r4Avk8bqhv6gZaOpizAzX3LwRZS9oi+NzhhVkh6?= =?us-ascii?Q?uqGoSGpcyP1oOSxnYziNOCF3/yM8xKDAeMRkdHr/k/Zxw1OtoWibp64E7gq1?= =?us-ascii?Q?BdpI/2DZ+VSfOdIMWbPnFkPjadp2qRx/Actiwk5vXkXQOuoOKz4SbzvqTwrF?= =?us-ascii?Q?6tYw3gYAddJi0rIxX+gZMhz3oup8CpjYpre0yX5yDlVDJJI/5EQ4n2QBBHTb?= =?us-ascii?Q?wp824esYUkpGH7RYGWRY4AdF1PHsNcV7mORv5/RrBeYQqZP74o+WFJ8v/9q2?= =?us-ascii?Q?sLXM30MQnkhOva/G9n/RrW39QWqaDHxhWHNIBU6PSTNcl8UiOxQFb6LOtz27?= =?us-ascii?Q?nxEbZh/uWMWEHUNl+ZdImCDzzPLe2MV9OvvPNnCkQ5bksb36wypcrwxJUYg2?= =?us-ascii?Q?wmCLncpV5Gi8TcVzUhDdkfzjsss6Fla/nvvzqUB7DaeOezRNSWAbcajxn3/x?= =?us-ascii?Q?s1wpb54a+Mf7Udnv2TvB2J/P6bjSC9axvtHcREMcT896RsVm1WZDeWQyIcaW?= =?us-ascii?Q?eELOBPDQEkNy+d4mHL7FbPDYXA1byNDKAbsKRRP5LHkob7sTHYuxNVtJvHAn?= =?us-ascii?Q?/8ALypIhwH1qs/P7msZPpZ7LDsf5TOoP/UD7iMDfheA5/RxB3LrqdNw22L+S?= =?us-ascii?Q?gHVVXYqgWilRojTNS0tppmIYy+HuVB1h6DNnZpBusfSCd8nnP1m3/ah8G2KF?= =?us-ascii?Q?61eW9AGpacgXlxrzYzn5l/grcVT5T873w3cI2iAB0Se9WmtniELeE7aKOrOv?= =?us-ascii?Q?8R6UyadF7U/NpBu/3kNH/VtZ40MOwHxuCGpH+mVA1SNW40MEqyHWgiSHgkrE?= =?us-ascii?Q?mr5RrNrQjjaVkBXSC93tU7u9d/lX8GXVLe8N3Ho8HJWzh6DqzeyCK4ACW19z?= =?us-ascii?Q?UDs1KRaVMMcyhef+mFfJL9A3?=\nX-Forefront-Antispam-Report-Untrusted: CIP:255.255.255.255;CTRY:;LANG:en;SCL:1;SRV:;IPV:NLI;SFV:NSPM;H:PAXPR09MB5021.eurprd09.prod.outlook.com;PTR:;CAT:NONE;SFS:(13230040)(366016)(1800799024)(376014)(38070700018);DIR:OUT;SFP:1102\nMIME-Version: 1.0\nX-MS-Exchange-Transport-CrossTenantHeadersStamped: VI0PR09MB7389\nX-Mimecast-Spam-Score: 0\nX-Mimecast-Originator: etoilegroup.com\nContent-Language: en-US\nContent-Type: multipart/related; boundary=\"_014_PAXPR09MB5021E1E1037A109F975F4D0CEC7D2PAXPR09MB5021eurp_\"; type=\"multipart/alternative\"\nReturn-Path: roselle.reyes@etoilegroup.com\nX-MS-Exchange-Organization-ExpirationStartTime: 07 Oct 2024 13:09:03.9801 (UTC)\nX-MS-Exchange-Organization-ExpirationStartTimeReason: OriginalSubmit\nX-MS-Exchange-Organization-ExpirationInterval: 1:00:00:00.0000000\nX-MS-Exchange-Organization-ExpirationIntervalReason: OriginalSubmit\nX-MS-Exchange-Organization-Network-Message-Id: 2e722fee-31e6-4675-d0f5-08dce6d137e0\nX-EOPAttributedMessage: 0\nX-EOPTenantAttributedMessage: 6ef8304c-f37b-42a5-a569-0a7d8249fbf3:0\nX-MS-Exchange-Organization-MessageDirectionality: Incoming\nX-MS-Exchange-Transport-CrossTenantHeadersStripped: DU2PEPF00028D12.eurprd03.prod.outlook.com\nX-MS-PublicTrafficType: Email\nX-MS-Exchange-Organization-AuthSource: DU2PEPF00028D12.eurprd03.prod.outlook.com\nX-MS-Exchange-Organization-AuthAs: Anonymous\nX-MS-Office365-Filtering-Correlation-Id-Prvs: d3f6d634-b0d6-4c94-3486-08dce6d13242\nX-MS-Exchange-AtpMessageProperties: SA|SL\nX-MS-Exchange-Organization-SCL: -1\nX-Microsoft-Antispam: BCL:0;ARA:13230040|31092699021|35042699022;\nX-Forefront-Antispam-Report: CIP:185.58.86.160;CTRY:GB;LANG:en;SCL:-1;SRV:;IPV:NLI;SFV:SKA;H:eu-smtp-delivery-160.mimecast.com;PTR:eu-smtp-delivery-160.mimecast.com;CAT:NONE;SFS:(13230040)(31092699021)(35042699022);DIR:INB;\nX-MS-Exchange-CrossTenant-OriginalArrivalTime: 07 Oct 2024 13:09:03.9332 (UTC)\nX-MS-Exchange-CrossTenant-Network-Message-Id: 2e722fee-31e6-4675-d0f5-08dce6d137e0\nX-MS-Exchange-CrossTenant-Id: 6ef8304c-f37b-42a5-a569-0a7d8249fbf3\nX-MS-Exchange-CrossTenant-AuthSource: DU2PEPF00028D12.eurprd03.prod.outlook.com\nX-MS-Exchange-CrossTenant-AuthAs: Anonymous\nX-MS-Exchange-CrossTenant-FromEntityHeader: Internet\nX-MS-Exchange-Transport-CrossTenantHeadersStamped: PAVPR05MB10022\nX-MS-Exchange-Transport-EndToEndLatency: 00:00:08.5138677\nX-MS-Exchange-Processed-By-BccFoldering: 15.20.7982.032\nX-Microsoft-Antispam-Mailbox-Delivery: ucf:0;jmr:0;auth:0;dest:I;ENG:(910001)(944506478)(944626604)(920097)(930097)(140003)(1420198);\nX-Microsoft-Antispam-Message-Info: =?us-ascii?Q?VYFgeecS0PTcKJIj3M1oaiRksEcraZIjBIkRFm6SzCKIlePfkYYTniol0HtM?= =?us-ascii?Q?dWs+FeQRh78UgqpgNHl7Rk2KFciVubmp0pGa8eJWYcp6qrV+lhNNBEwRChGg?= =?us-ascii?Q?ijWOd3oY75/v7i23i3rQ4wI18w3XOrm7ZuNqCCFqdM7gagh2zCa1qXVSPdaO?= =?us-ascii?Q?e9gtPdLYdFIFdUId51n4HGm9clN62t2q5WjP0vbR92ekE7o1Ig6RPKe7Etkv?= =?us-ascii?Q?hhgVQsBolOC1hEjkIQWeVz+no3pMrQdkAZhWT4bqBF2k78ODPfeVSIGbNx40?= =?us-ascii?Q?3oX8zxDBKyDTgDHf3F2d5F0x5xz+sdNO1JCyUCdhKkwE5yZsBkJ4R1lqo6AF?= =?us-ascii?Q?WUBBQCa95r7UuVZrNx8sCZpZjvsoNM/Rn+yRixVoiGlCQF+UUWSsJwD81NzU?= =?us-ascii?Q?eTwE3ALTdIHqC3tY1+Onj4rEuuVZhIVP6VOqjM+3fiDRVJbm4dfy8ikLhFe7?= =?us-ascii?Q?D1TAsUJucrFwevTM7E8MW88EG6i+fZAvGvZSBY59/p7dTfj6SgCTAE4pudwy?= =?us-ascii?Q?Ck6YV3dKiTFlCJzcyWXxnJ4Q5zBmEQfC0xq4Xq72GqRW2P09NO70U18uNoix?= =?us-ascii?Q?FXdbEM53bnGJOHBw8sis0V3zAuv4qx1H/glvjreNPuhowVc/Is+MVsv0A5K3?= =?us-ascii?Q?yIfcZjc+pQUhot+jrnTI+GnHRNM7XvLnWiR+cb7fGs9nnLCGHVOMXY11vzor?= =?us-ascii?Q?uVYVwWdLnrrrmLV8hEZhixquoQPiNB+DpRYNq1UhAD84JjOcbbGm6ReiQWlF?= =?us-ascii?Q?QP8TPG0IAsBbrh2PCRoi7fJYF/ZNQ1Mk0q/EimUKK9pC2BqIELxq14jpiadx?= =?us-ascii?Q?6RAYc6liQD66GlBtQUkeA4vLT155sz9S53zAAi7uy6W7ushBTkjFN6hQLCGs?= =?us-ascii?Q?4KYyzQbHP7SVj7jU8/LmpMugy5q+KXOyf3algXb2oV+Ed5oUlyTXSx7jBqoC?= =?us-ascii?Q?MGlnY13CKSXiUsCFY/ZXDrgRlU4i6eNDg3M7fenfzePrTnL41ruzcoexL99D?= =?us-ascii?Q?nzn1eXM2I73ABY72If5dYK4Xqe9gLp9Z11+wgaXH0Ar+uiL4/8p6NQmNJ1L/?= =?us-ascii?Q?KwLTd4FSSR6vGYnItDQusY4BfvUSWtozOcqqeHjOsFrq0hNPIgjEqs+ZzI1/?= =?us-ascii?Q?llZlUxaXYx1NviXH5fFHd7rRrHlHGm9kbT8dc69EsavUaznM/nEy1Z8ZFgqg?= =?us-ascii?Q?XgvOhi3tyjmR4ZIIKrAZgjFeSwckItL9U7k/sG/Dy6LjhDvxTERKc/vo+ehe?= =?us-ascii?Q?iPgwCrcHDsdvbpJqxGk7AJAwIrzrYc0qgoydR281ngn3yxwLyWm4VIDUL3P8?= =?us-ascii?Q?FDLvjwQ6mutyzJVkSbCjZP0CeJOTND2GImOw/JgfqO+RUObFi+SxsHdXWkLg?= =?us-ascii?Q?1nIWNoMAxez78cFMs5IUFEVF2rzh5M/+4zFOrLCiEKA4tAPECkVIkjb49QBZ?= =?us-ascii?Q?plbsQs2is9lEEXAGeSJ8Gid+6L/HGWJ9pLgR0rgczl1vfY9utA8jR/qYSLvC?= =?us-ascii?Q?IN25NdonTpTxeuILEvqzuuo2V7fRRz6tuV9tSKjmitaOyijotf1uzLLd7xXr?= =?us-ascii?Q?1SdgqfaMkPwWsIHyWd39fOHnKN6HAYYiDyhlPXnKw/Lya9cROjuo5PRV+Sq5?= =?us-ascii?Q?to44pWUKKycavdzHc5GIolalGI9TkTycJnO8uI2kpAoWv+MgOvdtZxWGmQ4c?= =?us-ascii?Q?IoJGasSBK1JuRAI0/woHt47YY3ivGhgVEG3qJnQFDBqgQd+NNRKrKKHZ6sYe?= =?us-ascii?Q?jWZILnzVdLO3LPVo1XiNqA2Mm7+f3DqoJaCkrpAfVG6psvWDad6Tid2N5wzp?= =?us-ascii?Q?k7eum7PN3fO8uSBssWC84fsWd/nYU+jIkLJMOMNmz6m6c/6R9qZmA3An4GLU?= =?us-ascii?Q?5GEkgM96fh4RbshoAfsQMMnvBQEms4W6eP9WStA6MW7kElhmxb/nZW35hP9q?= =?us-ascii?Q?dS271BUrWsjCQ5E6/1nY5qCN+Fmixn6PEEyAx+C/TbofRqeP157CAhOKi6NH?= =?us-ascii?Q?BdPzB3lhrQFHXOcwQHNwGKYlOKo4t3Rz4HcYy9TX+lc34McC1tLxtlM5DzIt?= =?us-ascii?Q?LDqImPGSPkjRDKvVROmuC4srUel1ecxz9My6AL9ce9uBQhfEvLPlz+wrCZGx?= =?us-ascii?Q?toz42fGkoep/?=",
      "start_pos": 3589,
      "end_pos": 11213,
      "chunk_index": 1,
      "chunk_size": 7624,
      "metadata": {
        "doc_id": "C1UKO3Y - theft incident in stores\\Headers\\C1UKO3Y_03.txt",
        "doc_path": "C:\\Users\\ASUS\\Desktop\\Outlook\\C1UKO3Y - theft incident in stores\\Headers\\C1UKO3Y_03.txt"
      }
    }
  ],
  "metadata": {
    "chunked_at": "2025-10-06T06:27:22.532666",
    "chunk_config": {
      "chunk_size": 1600,
      "chunk_overlap": 200,
      "min_chunk_size": 100,
      "respect_sentences": true,
      "respect_paragraphs": true,
      "base_max_chunks": 25,
      "progressive_scaling": true
    },
    "original_size": 11285
  }
}